fttransformer/__init__.py
fttransformer/model.py
tabtransformer/__init__.py
tabtransformer/model.py
utils/__init__.py
utils/batch.py
utils/device.py
utils/logger.py
tabular_transformers-0.1.1.dist-info/METADATA
tabular_transformers-0.1.1.dist-info/WHEEL
tabular_transformers-0.1.1.dist-info/top_level.txt
tabular_transformers-0.1.1.dist-info/RECORD
