Metadata-Version: 2.4
Name: tabular-transformers
Version: 0.1.1
Summary: Production-ready PyTorch implementations of Transformers for tabular data (numerical/categorical, multi-output, multi-label)
Home-page: https://github.com/duster-amigos/Tabular-Deep-Learning
Author: Shivansh Gupta
Author-email: duster.amigos05@gmail.com
Project-URL: Source, https://github.com/duster-amigos/Tabular-Deep-Learning
Project-URL: Documentation, https://github.com/duster-amigos/Tabular-Deep-Learning#readme
Classifier: Programming Language :: Python :: 3
Classifier: License :: OSI Approved :: MIT License
Classifier: Operating System :: OS Independent
Classifier: Intended Audience :: Science/Research
Classifier: Intended Audience :: Developers
Classifier: Topic :: Scientific/Engineering :: Artificial Intelligence
Classifier: Topic :: Software Development :: Libraries :: Python Modules
Requires-Python: >=3.8
Requires-Dist: torch>=2.2.0
Requires-Dist: numpy>=1.26.0
Requires-Dist: tqdm>=4.66.0
Requires-Dist: loguru>=0.7.2
Dynamic: author
Dynamic: author-email
Dynamic: classifier
Dynamic: description
Dynamic: description-content-type
Dynamic: home-page
Dynamic: project-url
Dynamic: requires-dist
Dynamic: requires-python
Dynamic: summary
